ChangeLog
LICENSE.GPL-2
MANIFEST.in
README.txt
setup.cfg
setup.py
bin/gracied
bin/make-dist-tarball
doc/HACKING.txt
doc/README.txt
doc/TODO.txt
doc/gracie-logo.svg
doc/gracied.8.txt
gracie/__init__.py
gracie/authorisation.py
gracie/authservice.py
gracie/httprequest.py
gracie/httpresponse.py
gracie/httpserver.py
gracie/pagetemplate.py
gracie/server.py
gracie/session.py
gracie.egg-info/PKG-INFO
gracie.egg-info/SOURCES.txt
gracie.egg-info/dependency_links.txt
gracie.egg-info/not-zip-safe
gracie.egg-info/requires.txt
gracie.egg-info/top_level.txt
gracie/version/__init__.py
gracie/version/version_info.py
test/__init__.py
test/scaffold.py
test/test_authorisation.py
test/test_authservice.py
test/test_gracied.py
test/test_httprequest.py
test/test_httpresponse.py
test/test_httpserver.py
test/test_pagetemplate.py
test/test_server.py
test/test_session.py